{
    "9698398a12a206a79c79a87eaa681445": {
        "node_id": "user1",
        "p_counter": {
            "banana": {
                "user1": 2
            }
        },
        "n_counter": {
            "apple": {
                "user1": 3
            },
            "cocacola": {
                "user1": 3
            },
            "banana": {
                "user1": 2
            }
        }
    },
    "8f97afbc42f4a95020de6d66dbd176b0": {
        "node_id": "user3",
        "p_counter": {
            "banana": {
                "user3": 2
            }
        },
        "n_counter": {
            "apple": {
                "user3": 3
            },
            "cocacola": {
                "user3": 3
            },
            "banana": {
                "user3": 2
            }
        }
    }
}